URLSearchParams/__init__.py
URLSearchParams-1.2.dist-info/LICENSE
URLSearchParams-1.2.dist-info/METADATA
URLSearchParams-1.2.dist-info/WHEEL
URLSearchParams-1.2.dist-info/top_level.txt
URLSearchParams-1.2.dist-info/RECORD
