Metadata-Version: 2.1
Name: URLSearchParams
Version: 1.2
Summary: The URLSearchParams interface defines utility methods to work with the query string of a URL.
Home-page: https://github.com/sijey-praveen/googlesearch.py
Author: Sijey Praveen
Author-email: cjpraveen@hotmail.com
License: UNKNOWN
Keywords: URLSearchParams Python,python3,sijey,sijey-praveen,sijey praveen,urlsearchparams,URLSearchParams
Platform: UNKNOWN
Requires-Python: >=3.6
License-File: LICENSE
